cli/__init__.py
cli/build/lib/cli/__init__.py
cli/build/lib/cli/auth.py
cli/build/lib/cli/config.py
cli/build/lib/cli/main.py
cli/build/lib/cli/build/lib/commands/__init__.py
cli/build/lib/cli/build/lib/commands/generate.py
cli/build/lib/cli/build/lib/commands/offline.py
cli/build/lib/cli/build/lib/commands/online.py
cli/build/lib/cli/build/lib/commands/useless.py
cli/build/lib/cli/build/lib/commands/utils.py
cli/build/lib/cli/commands/__init__.py
cli/build/lib/cli/commands/generate.py
cli/build/lib/cli/commands/offline.py
cli/build/lib/cli/commands/online.py
cli/build/lib/cli/commands/useless.py
cli/build/lib/cli/commands/utils.py
cli/cli/__init__.py
cli/cli/auth.py
cli/cli/config.py
cli/cli/main.py
cli/cli/build/lib/commands/__init__.py
cli/cli/build/lib/commands/generate.py
cli/cli/build/lib/commands/offline.py
cli/cli/build/lib/commands/online.py
cli/cli/build/lib/commands/useless.py
cli/cli/build/lib/commands/utils.py
cli/cli/commands/__init__.py
cli/cli/commands/generate.py
cli/cli/commands/offline.py
cli/cli/commands/online.py
cli/cli/commands/useless.py
cli/cli/commands/utils.py
models/__init__.py
models/install.py
models/prompts.py
models/run.py
shared/__init__.py
shared/file_utils.py
shared/prompt_builder.py
test_genie-1.0.0.dist-info/licenses/LICENSE
test_genie-1.0.0.dist-info/METADATA
test_genie-1.0.0.dist-info/WHEEL
test_genie-1.0.0.dist-info/entry_points.txt
test_genie-1.0.0.dist-info/top_level.txt
test_genie-1.0.0.dist-info/RECORD
