Metadata-Version: 2.4
Name: test-genie
Version: 1.0.0
Summary: AI-Powered Test Case Generation for Developers
Author-email: TestGenie Team <team@testgenie.dev>
License: MIT
Project-URL: Homepage, https://github.com/testgenie/testgenie
Project-URL: Repository, https://github.com/testgenie/testgenie
Project-URL: Documentation, https://docs.testgenie.dev
Project-URL: Issues, https://github.com/testgenie/testgenie/issues
Keywords: testing,ai,test-generation,cli
Classifier: Development Status :: 3 - Alpha
Classifier: Intended Audience :: Developers
Classifier: License :: OSI Approved :: MIT License
Classifier: Programming Language :: Python :: 3
Classifier: Programming Language :: Python :: 3.8
Classifier: Programming Language :: Python :: 3.9
Classifier: Programming Language :: Python :: 3.10
Classifier: Programming Language :: Python :: 3.11
Requires-Python: >=3.8
License-File: LICENSE
Requires-Dist: click>=8.1.7
Requires-Dist: requests>=2.31.0
Requires-Dist: pathlib2>=2.3.7
Provides-Extra: dev
Requires-Dist: pytest>=7.0.0; extra == "dev"
Requires-Dist: pytest-cov>=4.0.0; extra == "dev"
Requires-Dist: black>=22.0.0; extra == "dev"
Requires-Dist: flake8>=5.0.0; extra == "dev"
Requires-Dist: mypy>=1.0.0; extra == "dev"
Dynamic: license-file
